recon_stats/__init__.py
recon_stats/core.py
recon_stats/io.py
recon_stats_ldax-0.0.4.dist-info/METADATA
recon_stats_ldax-0.0.4.dist-info/WHEEL
recon_stats_ldax-0.0.4.dist-info/top_level.txt
recon_stats_ldax-0.0.4.dist-info/RECORD
