Metadata-Version: 2.1
Name: recon-stats-ldax
Version: 0.0.4
Summary: recon-stats-ldax is a simple package to parse stats files from Freesurfer recon-all
Home-page: http://github.com/VUIIS/recon-stats
Author: Scott Burns
Author-email: onealbao@gmail.com
License: BSD (3-clause)
Download-URL: http://github.com/VUIIS/recon-stats
Platform: any
Classifier: Development Status :: 2 - Pre-Alpha
Classifier: Intended Audience :: Developers
Classifier: Intended Audience :: Science/Research
Classifier: License :: OSI Approved :: BSD License
Classifier: Topic :: Software Development
Classifier: Topic :: Scientific/Engineering
Classifier: Operating System :: POSIX
Classifier: Operating System :: Unix
Classifier: Operating System :: MacOS
Classifier: Programming Language :: Python
Classifier: Programming Language :: Python :: 3.6
Classifier: Topic :: Scientific/Engineering
